{
    "serializationData": {
        "SerializedFormat": 2,
        "SerializedBytes": [],
        "ReferencedUnityObjects": [],
        "SerializedBytesString": "",
        "Prefab": {
            "instanceID": 0
        },
        "PrefabModificationsReferencedUnityObjects": [],
        "PrefabModifications": [],
        "SerializationNodes": [
            {
                "Name": "LayoutPath",
                "Entry": 7,
                "Data": "0|SEE.Game.DataPath, SEE"
            },
            {
                "Name": "Root",
                "Entry": 3,
                "Data": "2"
            },
            {
                "Name": "relativePath",
                "Entry": 1,
                "Data": ""
            },
            {
                "Name": "absolutePath",
                "Entry": 1,
                "Data": ""
            },
            {
                "Name": "",
                "Entry": 8,
                "Data": ""
            },
            {
                "Name": "HierarchicalEdges",
                "Entry": 7,
                "Data": "1|System.Collections.Generic.HashSet`1[[System.String, mscorlib]], System.Core"
            },
            {
                "Name": "",
                "Entry": 12,
                "Data": "4"
            },
            {
                "Name": "",
                "Entry": 1,
                "Data": "Enclosing"
            },
            {
                "Name": "",
                "Entry": 1,
                "Data": "Belongs_To"
            },
            {
                "Name": "",
                "Entry": 1,
                "Data": "Part_Of"
            },
            {
                "Name": "",
                "Entry": 1,
                "Data": "Defined_In"
            },
            {
                "Name": "",
                "Entry": 13,
                "Data": ""
            },
            {
                "Name": "",
                "Entry": 8,
                "Data": ""
            },
            {
                "Name": "nodeTypes",
                "Entry": 7,
                "Data": "2|System.Collections.Generic.Dictionary`2[[System.String, mscorlib],[System.Boolean, mscorlib]], mscorlib"
            },
            {
                "Name": "comparer",
                "Entry": 7,
                "Data": "3|System.Collections.Generic.GenericEqualityComparer`1[[System.String, mscorlib]], mscorlib"
            },
            {
                "Name": "",
                "Entry": 8,
                "Data": ""
            },
            {
                "Name": "",
                "Entry": 12,
                "Data": "8"
            },
            {
                "Name": "",
                "Entry": 7,
                "Data": ""
            },
            {
                "Name": "$k",
                "Entry": 1,
                "Data": "Namespace"
            },
            {
                "Name": "$v",
                "Entry": 5,
                "Data": "true"
            },
            {
                "Name": "",
                "Entry": 8,
                "Data": ""
            },
            {
                "Name": "",
                "Entry": 7,
                "Data": ""
            },
            {
                "Name": "$k",
                "Entry": 1,
                "Data": "Class"
            },
            {
                "Name": "$v",
                "Entry": 5,
                "Data": "true"
            },
            {
                "Name": "",
                "Entry": 8,
                "Data": ""
            },
            {
                "Name": "",
                "Entry": 7,
                "Data": ""
            },
            {
                "Name": "$k",
                "Entry": 1,
                "Data": "Member"
            },
            {
                "Name": "$v",
                "Entry": 5,
                "Data": "true"
            },
            {
                "Name": "",
                "Entry": 8,
                "Data": ""
            },
            {
                "Name": "",
                "Entry": 7,
                "Data": ""
            },
            {
                "Name": "$k",
                "Entry": 1,
                "Data": "Method"
            },
            {
                "Name": "$v",
                "Entry": 5,
                "Data": "true"
            },
            {
                "Name": "",
                "Entry": 8,
                "Data": ""
            },
            {
                "Name": "",
                "Entry": 7,
                "Data": ""
            },
            {
                "Name": "$k",
                "Entry": 1,
                "Data": "Type"
            },
            {
                "Name": "$v",
                "Entry": 5,
                "Data": "true"
            },
            {
                "Name": "",
                "Entry": 8,
                "Data": ""
            },
            {
                "Name": "",
                "Entry": 7,
                "Data": ""
            },
            {
                "Name": "$k",
                "Entry": 1,
                "Data": "Constant"
            },
            {
                "Name": "$v",
                "Entry": 5,
                "Data": "true"
            },
            {
                "Name": "",
                "Entry": 8,
                "Data": ""
            },
            {
                "Name": "",
                "Entry": 7,
                "Data": ""
            },
            {
                "Name": "$k",
                "Entry": 1,
                "Data": "Class_Template"
            },
            {
                "Name": "$v",
                "Entry": 5,
                "Data": "true"
            },
            {
                "Name": "",
                "Entry": 8,
                "Data": ""
            },
            {
                "Name": "",
                "Entry": 7,
                "Data": ""
            },
            {
                "Name": "$k",
                "Entry": 1,
                "Data": "Interface_Template"
            },
            {
                "Name": "$v",
                "Entry": 5,
                "Data": "true"
            },
            {
                "Name": "",
                "Entry": 8,
                "Data": ""
            },
            {
                "Name": "",
                "Entry": 13,
                "Data": ""
            },
            {
                "Name": "",
                "Entry": 8,
                "Data": ""
            },
            {
                "Name": "LeafNodeColorRange",
                "Entry": 7,
                "Data": "SEE.Game.ColorRange, SEE"
            },
            {
                "Name": "lower",
                "Entry": 7,
                "Data": "UnityEngine.Color, UnityEngine.CoreModule"
            },
            {
                "Name": "",
                "Entry": 4,
                "Data": "1"
            },
            {
                "Name": "",
                "Entry": 4,
                "Data": "1"
            },
            {
                "Name": "",
                "Entry": 4,
                "Data": "1"
            },
            {
                "Name": "",
                "Entry": 4,
                "Data": "1"
            },
            {
                "Name": "",
                "Entry": 8,
                "Data": ""
            },
            {
                "Name": "upper",
                "Entry": 7,
                "Data": "UnityEngine.Color, UnityEngine.CoreModule"
            },
            {
                "Name": "",
                "Entry": 4,
                "Data": "1"
            },
            {
                "Name": "",
                "Entry": 4,
                "Data": "0"
            },
            {
                "Name": "",
                "Entry": 4,
                "Data": "0"
            },
            {
                "Name": "",
                "Entry": 4,
                "Data": "1"
            },
            {
                "Name": "",
                "Entry": 8,
                "Data": ""
            },
            {
                "Name": "NumberOfColors",
                "Entry": 3,
                "Data": "10"
            },
            {
                "Name": "",
                "Entry": 8,
                "Data": ""
            },
            {
                "Name": "InnerNodeColorRange",
                "Entry": 7,
                "Data": "SEE.Game.ColorRange, SEE"
            },
            {
                "Name": "lower",
                "Entry": 7,
                "Data": "UnityEngine.Color, UnityEngine.CoreModule"
            },
            {
                "Name": "",
                "Entry": 4,
                "Data": "1"
            },
            {
                "Name": "",
                "Entry": 4,
                "Data": "1"
            },
            {
                "Name": "",
                "Entry": 4,
                "Data": "1"
            },
            {
                "Name": "",
                "Entry": 4,
                "Data": "1"
            },
            {
                "Name": "",
                "Entry": 8,
                "Data": ""
            },
            {
                "Name": "upper",
                "Entry": 7,
                "Data": "UnityEngine.Color, UnityEngine.CoreModule"
            },
            {
                "Name": "",
                "Entry": 4,
                "Data": "1"
            },
            {
                "Name": "",
                "Entry": 4,
                "Data": "0.921568632"
            },
            {
                "Name": "",
                "Entry": 4,
                "Data": "0.0156862754"
            },
            {
                "Name": "",
                "Entry": 4,
                "Data": "1"
            },
            {
                "Name": "",
                "Entry": 8,
                "Data": ""
            },
            {
                "Name": "NumberOfColors",
                "Entry": 3,
                "Data": "10"
            },
            {
                "Name": "",
                "Entry": 8,
                "Data": ""
            },
            {
                "Name": "CoseGraphSettings",
                "Entry": 7,
                "Data": "4|SEE.Layout.NodeLayouts.Cose.CoseGraphSettings, SEE"
            },
            {
                "Name": "EdgeLength",
                "Entry": 3,
                "Data": "20"
            },
            {
                "Name": "UseSmartIdealEdgeCalculation",
                "Entry": 5,
                "Data": "false"
            },
            {
                "Name": "UseSmartMultilevelScaling",
                "Entry": 5,
                "Data": "false"
            },
            {
                "Name": "PerLevelIdealEdgeLengthFactor",
                "Entry": 4,
                "Data": "0.1"
            },
            {
                "Name": "UseSmartRepulsionRangeCalculation",
                "Entry": 5,
                "Data": "false"
            },
            {
                "Name": "GravityStrength",
                "Entry": 4,
                "Data": "0.8"
            },
            {
                "Name": "CompoundGravityStrength",
                "Entry": 4,
                "Data": "1.5"
            },
            {
                "Name": "RepulsionStrength",
                "Entry": 4,
                "Data": "50"
            },
            {
                "Name": "multiLevelScaling",
                "Entry": 5,
                "Data": "false"
            },
            {
                "Name": "ListDirToggle",
                "Entry": 7,
                "Data": "5|System.Collections.Generic.Dictionary`2[[System.String, mscorlib],[System.Boolean, mscorlib]], mscorlib"
            },
            {
                "Name": "comparer",
                "Entry": 7,
                "Data": "6|System.Collections.Generic.GenericEqualityComparer`1[[System.String, mscorlib]], mscorlib"
            },
            {
                "Name": "",
                "Entry": 8,
                "Data": ""
            },
            {
                "Name": "",
                "Entry": 12,
                "Data": "0"
            },
            {
                "Name": "",
                "Entry": 13,
                "Data": ""
            },
            {
                "Name": "",
                "Entry": 8,
                "Data": ""
            },
            {
                "Name": "DirNodeLayout",
                "Entry": 7,
                "Data": "7|System.Collections.Generic.Dictionary`2[[System.String, mscorlib],[SEE.Layout.NodeLayouts.NodeLayoutKind, SEE]], mscorlib"
            },
            {
                "Name": "comparer",
                "Entry": 9,
                "Data": "6"
            },
            {
                "Name": "",
                "Entry": 12,
                "Data": "0"
            },
            {
                "Name": "",
                "Entry": 13,
                "Data": ""
            },
            {
                "Name": "",
                "Entry": 8,
                "Data": ""
            },
            {
                "Name": "DirShape",
                "Entry": 7,
                "Data": "8|System.Collections.Generic.Dictionary`2[[System.String, mscorlib],[SEE.Game.AbstractSEECity+InnerNodeKinds, SEE]], mscorlib"
            },
            {
                "Name": "comparer",
                "Entry": 9,
                "Data": "6"
            },
            {
                "Name": "",
                "Entry": 12,
                "Data": "0"
            },
            {
                "Name": "",
                "Entry": 13,
                "Data": ""
            },
            {
                "Name": "",
                "Entry": 8,
                "Data": ""
            },
            {
                "Name": "rootDirs",
                "Entry": 7,
                "Data": "9|System.Collections.Generic.List`1[[SEE.DataModel.DG.Node, SEE]], mscorlib"
            },
            {
                "Name": "",
                "Entry": 12,
                "Data": "0"
            },
            {
                "Name": "",
                "Entry": 13,
                "Data": ""
            },
            {
                "Name": "",
                "Entry": 8,
                "Data": ""
            },
            {
                "Name": "show",
                "Entry": 7,
                "Data": "10|System.Collections.Generic.Dictionary`2[[System.String, mscorlib],[System.Boolean, mscorlib]], mscorlib"
            },
            {
                "Name": "comparer",
                "Entry": 9,
                "Data": "6"
            },
            {
                "Name": "",
                "Entry": 12,
                "Data": "0"
            },
            {
                "Name": "",
                "Entry": 13,
                "Data": ""
            },
            {
                "Name": "",
                "Entry": 8,
                "Data": ""
            },
            {
                "Name": "showGraphListing",
                "Entry": 5,
                "Data": "true"
            },
            {
                "Name": "loadedForNodeTypes",
                "Entry": 7,
                "Data": "11|System.Collections.Generic.Dictionary`2[[System.String, mscorlib],[System.Boolean, mscorlib]], mscorlib"
            },
            {
                "Name": "comparer",
                "Entry": 9,
                "Data": "6"
            },
            {
                "Name": "",
                "Entry": 12,
                "Data": "0"
            },
            {
                "Name": "",
                "Entry": 13,
                "Data": ""
            },
            {
                "Name": "",
                "Entry": 8,
                "Data": ""
            },
            {
                "Name": "useCalculationParameter",
                "Entry": 5,
                "Data": "true"
            },
            {
                "Name": "useIterativeCalculation",
                "Entry": 5,
                "Data": "false"
            },
            {
                "Name": "",
                "Entry": 8,
                "Data": ""
            },
            {
                "Name": "Measurements",
                "Entry": 7,
                "Data": "12|System.Collections.Generic.SortedDictionary`2[[System.String, mscorlib],[System.String, mscorlib]], System"
            },
            {
                "Name": "",
                "Entry": 12,
                "Data": "0"
            },
            {
                "Name": "",
                "Entry": 13,
                "Data": ""
            },
            {
                "Name": "",
                "Entry": 8,
                "Data": ""
            },
            {
                "Name": "SubLayoutsInnerNodes",
                "Entry": 7,
                "Data": "13|System.Collections.Generic.Dictionary`2[[SEE.Layout.NodeLayouts.NodeLayoutKind, SEE],[System.String, mscorlib]], mscorlib"
            },
            {
                "Name": "comparer",
                "Entry": 7,
                "Data": "14|System.Collections.Generic.EnumEqualityComparer`1[[SEE.Layout.NodeLayouts.NodeLayoutKind, SEE]], mscorlib"
            },
            {
                "Name": "",
                "Entry": 12,
                "Data": "0"
            },
            {
                "Name": "",
                "Entry": 13,
                "Data": ""
            },
            {
                "Name": "",
                "Entry": 8,
                "Data": ""
            },
            {
                "Name": "",
                "Entry": 12,
                "Data": "7"
            },
            {
                "Name": "",
                "Entry": 7,
                "Data": ""
            },
            {
                "Name": "$k",
                "Entry": 3,
                "Data": "1"
            },
            {
                "Name": "$v",
                "Entry": 1,
                "Data": "Balloon"
            },
            {
                "Name": "",
                "Entry": 8,
                "Data": ""
            },
            {
                "Name": "",
                "Entry": 7,
                "Data": ""
            },
            {
                "Name": "$k",
                "Entry": 3,
                "Data": "4"
            },
            {
                "Name": "$v",
                "Entry": 1,
                "Data": "CirclePacking"
            },
            {
                "Name": "",
                "Entry": 8,
                "Data": ""
            },
            {
                "Name": "",
                "Entry": 7,
                "Data": ""
            },
            {
                "Name": "$k",
                "Entry": 3,
                "Data": "6"
            },
            {
                "Name": "$v",
                "Entry": 1,
                "Data": "CompoundSpringEmbedder"
            },
            {
                "Name": "",
                "Entry": 8,
                "Data": ""
            },
            {
                "Name": "",
                "Entry": 7,
                "Data": ""
            },
            {
                "Name": "$k",
                "Entry": 3,
                "Data": "0"
            },
            {
                "Name": "$v",
                "Entry": 1,
                "Data": "EvoStreets"
            },
            {
                "Name": "",
                "Entry": 8,
                "Data": ""
            },
            {
                "Name": "",
                "Entry": 7,
                "Data": ""
            },
            {
                "Name": "$k",
                "Entry": 3,
                "Data": "7"
            },
            {
                "Name": "$v",
                "Entry": 1,
                "Data": "FromFile"
            },
            {
                "Name": "",
                "Entry": 8,
                "Data": ""
            },
            {
                "Name": "",
                "Entry": 7,
                "Data": ""
            },
            {
                "Name": "$k",
                "Entry": 3,
                "Data": "2"
            },
            {
                "Name": "$v",
                "Entry": 1,
                "Data": "RectanglePacking"
            },
            {
                "Name": "",
                "Entry": 8,
                "Data": ""
            },
            {
                "Name": "",
                "Entry": 7,
                "Data": ""
            },
            {
                "Name": "$k",
                "Entry": 3,
                "Data": "3"
            },
            {
                "Name": "$v",
                "Entry": 1,
                "Data": "Treemap"
            },
            {
                "Name": "",
                "Entry": 8,
                "Data": ""
            },
            {
                "Name": "",
                "Entry": 13,
                "Data": ""
            },
            {
                "Name": "",
                "Entry": 8,
                "Data": ""
            },
            {
                "Name": "SubLayoutsLeafNodes",
                "Entry": 7,
                "Data": "15|System.Collections.Generic.Dictionary`2[[SEE.Layout.NodeLayouts.NodeLayoutKind, SEE],[System.String, mscorlib]], mscorlib"
            },
            {
                "Name": "comparer",
                "Entry": 9,
                "Data": "14"
            },
            {
                "Name": "",
                "Entry": 12,
                "Data": "8"
            },
            {
                "Name": "",
                "Entry": 7,
                "Data": ""
            },
            {
                "Name": "$k",
                "Entry": 3,
                "Data": "1"
            },
            {
                "Name": "$v",
                "Entry": 1,
                "Data": "Balloon"
            },
            {
                "Name": "",
                "Entry": 8,
                "Data": ""
            },
            {
                "Name": "",
                "Entry": 7,
                "Data": ""
            },
            {
                "Name": "$k",
                "Entry": 3,
                "Data": "4"
            },
            {
                "Name": "$v",
                "Entry": 1,
                "Data": "CirclePacking"
            },
            {
                "Name": "",
                "Entry": 8,
                "Data": ""
            },
            {
                "Name": "",
                "Entry": 7,
                "Data": ""
            },
            {
                "Name": "$k",
                "Entry": 3,
                "Data": "6"
            },
            {
                "Name": "$v",
                "Entry": 1,
                "Data": "CompoundSpringEmbedder"
            },
            {
                "Name": "",
                "Entry": 8,
                "Data": ""
            },
            {
                "Name": "",
                "Entry": 7,
                "Data": ""
            },
            {
                "Name": "$k",
                "Entry": 3,
                "Data": "0"
            },
            {
                "Name": "$v",
                "Entry": 1,
                "Data": "EvoStreets"
            },
            {
                "Name": "",
                "Entry": 8,
                "Data": ""
            },
            {
                "Name": "",
                "Entry": 7,
                "Data": ""
            },
            {
                "Name": "$k",
                "Entry": 3,
                "Data": "7"
            },
            {
                "Name": "$v",
                "Entry": 1,
                "Data": "FromFile"
            },
            {
                "Name": "",
                "Entry": 8,
                "Data": ""
            },
            {
                "Name": "",
                "Entry": 7,
                "Data": ""
            },
            {
                "Name": "$k",
                "Entry": 3,
                "Data": "5"
            },
            {
                "Name": "$v",
                "Entry": 1,
                "Data": "Manhattan"
            },
            {
                "Name": "",
                "Entry": 8,
                "Data": ""
            },
            {
                "Name": "",
                "Entry": 7,
                "Data": ""
            },
            {
                "Name": "$k",
                "Entry": 3,
                "Data": "2"
            },
            {
                "Name": "$v",
                "Entry": 1,
                "Data": "RectanglePacking"
            },
            {
                "Name": "",
                "Entry": 8,
                "Data": ""
            },
            {
                "Name": "",
                "Entry": 7,
                "Data": ""
            },
            {
                "Name": "$k",
                "Entry": 3,
                "Data": "3"
            },
            {
                "Name": "$v",
                "Entry": 1,
                "Data": "Treemap"
            },
            {
                "Name": "",
                "Entry": 8,
                "Data": ""
            },
            {
                "Name": "",
                "Entry": 13,
                "Data": ""
            },
            {
                "Name": "",
                "Entry": 8,
                "Data": ""
            },
            {
                "Name": "singleRoot",
                "Entry": 6,
                "Data": ""
            }
        ]
    },
    "LayoutPath": {
        "Root": 2,
        "relativePath": "",
        "absolutePath": ""
    },
    "jsonDirectory": "C:\\Users\\49152\\Documents\\BachelorProjekt_SEE\\SEE\\Assets",
    "WidthMetric": "Metric.Number_of_Tokens",
    "HeightMetric": "Metric.Clone_Rate",
    "DepthMetric": "Metric.LOC",
    "LeafStyleMetric": "Metric.Complexity",
    "ShowLabel": true,
    "LeafLabelDistance": 0.20000000298023225,
    "LeafLabelFontSize": 0.4000000059604645,
    "ArchitectureIssue": "Metric.Architecture_Violations",
    "CloneIssue": "Metric.Clone",
    "CycleIssue": "Metric.Cycle",
    "Dead_CodeIssue": "Metric.Dead_Code",
    "MetricIssue": "Metric.Metric",
    "StyleIssue": "Metric.Style",
    "UniversalIssue": "Metric.Universal",
    "ArchitectureIssue_SUM": "Metric.Architecture_Violations_SUM",
    "CloneIssue_SUM": "Metric.Clone_SUM",
    "CycleIssue_SUM": "Metric.Cycle_SUM",
    "Dead_CodeIssue_SUM": "Metric.Dead_Code_SUM",
    "MetricIssue_SUM": "Metric.Metric_SUM",
    "StyleIssue_SUM": "Metric.Style_SUM",
    "UniversalIssue_SUM": "Metric.Universal_SUM",
    "InnerDonutMetric": "Metric.IssuesTotal",
    "InnerNodeHeightMetric": "",
    "InnerNodeStyleMetric": "Metric.IssuesTotal",
    "InnerNodeShowLabel": true,
    "InnerNodeLabelDistance": 0.20000000298023225,
    "InnerNodeLabelFontSize": 0.4000000059604645,
    "MinimalBlockLength": 0.10000000149011612,
    "MaximalBlockLength": 100.0,
    "LeafObjects": 0,
    "InnerNodeObjects": 0,
    "NodeLayout": 3,
    "EdgeLayout": 0,
    "ZScoreScale": false,
    "EdgeWidth": 0.30000001192092898,
    "ShowErosions": false,
    "MaxErosionWidth": 1.0,
    "EdgesAboveBlocks": true,
    "Tension": 0.8500000238418579,
    "RDP": 0.05000000074505806,
    "calculateMeasurements": false,
    "maxRevisionsToLoad": 500,
    "MarkerHeight": 0.20000000298023225,
    "MarkerWidth": 0.009999999776482582,
    "AdditionBeamColor": {
        "r": 0.0,
        "g": 1.0,
        "b": 0.0,
        "a": 1.0
    },
    "ChangeBeamColor": {
        "r": 1.0,
        "g": 0.9215686321258545,
        "b": 0.01568627543747425,
        "a": 1.0
    },
    "DeletionBeamColor": {
        "r": 0.0,
        "g": 0.0,
        "b": 0.0,
        "a": 1.0
    },
    "GXLDirectory": {
        "Root": 0,
        "relativePath": "/Data/GXL/animation-clones",
        "absolutePath": "C:/Users/49152/Desktop/Codefacts_Test"
    },
    "isAnSEECityEvolutionObject": "isAnSEECityEvolutionObject"
}